LICENSE
MANIFEST.in
README.rst
helga_meant_to_say.py
setup.py
helga_meant_to_say.egg-info/PKG-INFO
helga_meant_to_say.egg-info/SOURCES.txt
helga_meant_to_say.egg-info/dependency_links.txt
helga_meant_to_say.egg-info/entry_points.txt
helga_meant_to_say.egg-info/top_level.txt
helga_meant_to_say.egg-info/zip-safe